zef/LICENSE.pybind11
zef/LICENSE
zef/_version.py
zef/LICENSE.websocketpp
zef/auth.html
zef/COPYING.asio
zef/LICENSE.asio
zef/LICENSE.jwt-cpp
zef/LICENSE.pybind_json
zef/pyzef.cpython-310-darwin.so
zef/__init__.py
zef/LICENSE.libzef
zef/LICENSE.zstd
zef/LICENSE.phmap
zef/LICENSE.libarchive
zef/LICENSE.yaml-cpp
zef/LICENSE.libcurl
zef/LICENSE.rangesv3
zef/LICENSE.nlohmann_json
zef/ui/__init__.py
zef/ui/visualizations.py
zef/ui/zef_rich.py
zef/ui/components.py
zef/experimental/sql_import.py
zef/experimental/__init__.py
zef/experimental/repl_interface.py
zef/experimental/subgraph.py
zef/experimental/networkx.py
zef/experimental/zefui/server_temp.py
zef/experimental/zefui/server.py
zef/experimental/zefui/__init__.py
zef/experimental/zefui/graph_crawler.py
zef/experimental/importers/__init__.py
zef/experimental/importers/general.py
zef/experimental/sql_ui/ui.py
zef/experimental/sql_ui/__init__.py
zef/experimental/sql_ui/wizard_sdl2.py
zef/experimental/sql_ui/wizard_pygame.py
zef/experimental/sql_ui/wizard.py
zef/experimental/sql_ui/wizard_glfw.py
zef/core/op_structs.py
zef/core/abstract_raes.py
zef/core/symbolic_expression.py
zef/core/user_value_type.py
zef/core/streams.py
zef/core/units.py
zef/core/_ops.py
zef/core/_error.py
zef/core/zef_functions.py
zef/core/__init__.py
zef/core/overrides.py
zef/core/graph_delta.py
zef/core/logger.py
zef/core/_decimal.py
zef/core/patching.py
zef/core/_image.py
zef/core/generators.py
zef/core/_core.py
zef/core/graph_events.py
zef/core/z_expression.py
zef/core/flat_graph.py
zef/core/_bytes.py
zef/core/delegates.py
zef/core/pure_utils.py
zef/core/serialization.py
zef/core/graph_slice.py
zef/core/VT/python_types.py
zef/core/VT/extended_containers.py
zef/core/VT/generate_pyi.py
zef/core/VT/__init__.py
zef/core/VT/value_type.py
zef/core/VT/libzef_types.py
zef/core/VT/later.py
zef/core/VT/rae_types.py
zef/core/VT/sets.py
zef/core/VT/external.py
zef/core/VT/helpers.py
zef-0.17.1.dist-info/RECORD
zef-0.17.1.dist-info/WHEEL
zef-0.17.1.dist-info/top_level.txt
zef-0.17.1.dist-info/METADATA
