Metadata-Version: 2.1
Name: zef
Version: 0.17.1
Summary: A data-oriented toolkit for graph data
Home-page: https://github.com/zefhub/zef
Author: ZefHub.io
Author-email: hello@zefhub.io
Classifier: Programming Language :: Python :: 3
Classifier: License :: OSI Approved :: Apache Software License
Classifier: Operating System :: OS Independent
Requires-Python: >=3.7
Requires-Dist: Rx (>=3.1.1)
Requires-Dist: websockets (>=10.1)
Requires-Dist: pyfunctional (>=1.3.0)
Requires-Dist: toml (>=0.10.1)
Requires-Dist: dateparser (>=0.7.6)
Requires-Dist: cogapp (>=3.0.0)
Requires-Dist: structlog (>=20.1.0)
Requires-Dist: colorama (>=0.4.3)
Requires-Dist: ariadne (>=0.12.0)
Requires-Dist: pyperclip (>=1.8.2)
Requires-Dist: pytz (>=2021.1)
Requires-Dist: more-itertools (>=4.2.0)
Requires-Dist: art (>=5.2)
Requires-Dist: PyYAML (>=6.0)
Requires-Dist: pandas (>=1.3.5)
Requires-Dist: case-converter (>=1.0.2)
Requires-Dist: watchdog (>=2.1.9)
Requires-Dist: frozendict (>=2.3.4)
Requires-Dist: rich (>=12.6.0)
Requires-Dist: blake3 (>=0.3.1)
